expmiband2/__init__.py
expmiband2/authsession.py
expmiband2/band2.py
expmiband2-0.1.3.dist-info/LICENSE
expmiband2-0.1.3.dist-info/WHEEL
expmiband2-0.1.3.dist-info/METADATA
expmiband2-0.1.3.dist-info/RECORD
