Metadata-Version: 2.1
Name: expmiband2
Version: 0.1.3
Summary: Python API for communicating with MiBand2
Author-email: Anton Ptashnik <iavtomator@gmail.com>
Requires-Python: >=3.5
Classifier: License :: OSI Approved :: MIT License
Requires-Dist: bleak==0.20.1
Requires-Dist: pyaes==1.6.1
Requires-Dist: pytest >= 7.3.0 ; extra == "test"
Project-URL: Documentation, https://github.com/anton-ptashnik/expmiband2-api-py
Project-URL: Home, https://github.com/anton-ptashnik/expmiband2-api-py
Project-URL: Source, https://github.com/anton-ptashnik/expmiband2-api-py
Provides-Extra: test
